README.md
pyproject.toml
setup.py
autowork_cli/__init__.py
autowork_cli/__main__.py
autowork_cli.egg-info/PKG-INFO
autowork_cli.egg-info/SOURCES.txt
autowork_cli.egg-info/dependency_links.txt
autowork_cli.egg-info/entry_points.txt
autowork_cli.egg-info/top_level.txt
autowork_cli/cf/__init__.py
autowork_cli/cf/cf_cmd.py
autowork_cli/common/__init__.py
autowork_cli/common/config/BaseURLConfig.py
autowork_cli/common/config/BusinessURLConfig.py
autowork_cli/common/config/ClientConfig.py
autowork_cli/common/config/ConfigModel.py
autowork_cli/common/config/LoginConfig.py
autowork_cli/common/config/PublicConfig.py
autowork_cli/common/config/__init__.py
autowork_cli/common/config/template/__init__.py
autowork_cli/common/config/template/hello_world_template.py
autowork_cli/common/config/template/pyproject_template.py
autowork_cli/common/config/template/sandbox_readme_template.py
autowork_cli/common/config/template/sandbox_start_template.py
autowork_cli/common/lang/__init__.py
autowork_cli/common/lang/async_requests.py
autowork_cli/common/lang/dictclass.py
autowork_cli/common/lang/logger_setting.py
autowork_cli/common/lang/singleton.py
autowork_cli/common/lang/sync.py
autowork_cli/common/local/__init__.py
autowork_cli/common/local/clientinfo.py
autowork_cli/common/log/AwLogger.py
autowork_cli/common/log/LogManager.py
autowork_cli/common/log/__init__.py
autowork_cli/common/request/CybotronAsyncClient.py
autowork_cli/common/request/CybotronSyncClient.py
autowork_cli/common/request/__init__.py
autowork_cli/common/request/forward_request.py
autowork_cli/file/CosFileManager.py
autowork_cli/file/__init__.py
autowork_cli/file/file_cmd.py
autowork_cli/flow/__init__.py
autowork_cli/flow/flow_cmd.py
autowork_cli/log/__init__.py
autowork_cli/log/log_cmd.py
autowork_cli/login/__init__.py
autowork_cli/login/login_cmd.py
autowork_cli/repository/__init__.py
autowork_cli/repository/cybotron/__init__.py
autowork_cli/repository/cybotron/model/__init__.py
autowork_cli/repository/cybotron/model/flowobj.py
autowork_cli/repository/cybotron/model/metadataobj.py
autowork_cli/repository/cybotron/service/__init__.py
autowork_cli/repository/cybotron/service/common_access.py
