Metadata-Version: 2.1
Name: autowork-cli
Version: 1.5.13
Summary: 沙盒函数命令行工具
Requires-Python: >=3.11
